{
  "features": [
    {
      "data": {
        "feature": {
          "block": {
            "state": {
              "Name": "minecraft:basalt",
              "Properties": {
                "axis": "y"
              }
            },
            "type": "minecraft:simple_state_provider"
          },
          "can_replace": {
            "predicates": [
              {
                "tag": "minecraft:air",
                "type": "minecraft:matching_block_tag"
              },
              {
                "predicates": [
                  {
                    "blocks": "minecraft:lava",
                    "type": "minecraft:matching_blocks"
                  },
                  {
                    "max_inclusive": {
                      "relative_to_sea_level": 0
                    },
                    "min_inclusive": {
                      "above_bottom": 0
                    },
                    "type": "minecraft:height_range"
                  }
                ],
                "type": "minecraft:all_of"
              }
            ],
            "type": "minecraft:any_of"
          },
          "cannot_place_on": "#minecraft:cannot_place_basalt_pillar_on",
          "cluster_reach": 5,
          "column_count": 50,
          "column_reach": {
            "max_inclusive": 3,
            "min_inclusive": 2,
            "type": "minecraft:uniform"
          },
          "continue_through": {
            "blocks": "minecraft:basalt",
            "type": "minecraft:matching_blocks"
          },
          "height": {
            "max_inclusive": 10,
            "min_inclusive": 5,
            "type": "minecraft:uniform"
          },
          "type": "minecraft:stepped_column_cluster"
        },
        "placement": []
      },
      "weight": 9
    },
    {
      "data": {
        "feature": {
          "block": {
            "state": {
              "Name": "minecraft:basalt",
              "Properties": {
                "axis": "y"
              }
            },
            "type": "minecraft:simple_state_provider"
          },
          "can_replace": {
            "predicates": [
              {
                "tag": "minecraft:air",
                "type": "minecraft:matching_block_tag"
              },
              {
                "predicates": [
                  {
                    "blocks": "minecraft:lava",
                    "type": "minecraft:matching_blocks"
                  },
                  {
                    "max_inclusive": {
                      "relative_to_sea_level": 0
                    },
                    "min_inclusive": {
                      "above_bottom": 0
                    },
                    "type": "minecraft:height_range"
                  }
                ],
                "type": "minecraft:all_of"
              }
            ],
            "type": "minecraft:any_of"
          },
          "cannot_place_on": "#minecraft:cannot_place_basalt_pillar_on",
          "cluster_reach": 8,
          "column_count": 15,
          "column_reach": {
            "max_inclusive": 3,
            "min_inclusive": 2,
            "type": "minecraft:uniform"
          },
          "continue_through": {
            "blocks": "minecraft:basalt",
            "type": "minecraft:matching_blocks"
          },
          "height": {
            "max_inclusive": 10,
            "min_inclusive": 5,
            "type": "minecraft:uniform"
          },
          "type": "minecraft:stepped_column_cluster"
        },
        "placement": []
      },
      "weight": 1
    }
  ],
  "type": "minecraft:weighted_random_selector"
}