{"pools":[{"bonus_rolls":0.0,"entries":[{"conditions":[{"block":"minecraft:sweet_berry_bush","condition":"minecraft:block_state_property","properties":{"age":"3"}}],"functions":[{"add":false,"count":1.0,"function":"minecraft:set_count"}],"name":"minecraft:sweet_berries","type":"minecraft:item"}],"rolls":1.0},{"bonus_rolls":0.0,"entries":[{"functions":[{"add":false,"count":{"max":2.0,"min":1.0,"type":"minecraft:uniform"},"function":"minecraft:set_count"}],"name":"minecraft:sweet_berries","type":"minecraft:item"}],"rolls":1.0}],"random_sequence":"minecraft:harvest/sweet_berry_bush","type":"minecraft:block_interact"}