{
  "criteria": {
    "has_cornflower": {
      "conditions": {
        "entity": [
          {
            "condition": "minecraft:entity_properties",
            "entity": "this",
            "predicate": {
              "type": "minecraft:living_block",
              "type_specific": {
                "item": {
                  "items": "minecraft:cornflower"
                },
                "type": "minecraft:living_block"
              }
            }
          }
        ]
      },
      "trigger": "minecraft:summoned_entity"
    },
    "has_the_recipe": {
      "conditions": {
        "recipe": "minecraft:blue_dye_from_cornflower"
      },
      "trigger": "minecraft:recipe_unlocked"
    }
  },
  "parent": "minecraft:recipes/root",
  "requirements": [
    [
      "has_the_recipe",
      "has_cornflower"
    ]
  ],
  "rewards": {
    "recipes": [
      "minecraft:blue_dye_from_cornflower"
    ]
  }
}